leetcron/__init__.py
leetcron/leetcode_to_github.py
leetcron-0.1.0.data/scripts/leetcron
leetcron-0.1.0.dist-info/LICENSE
leetcron-0.1.0.dist-info/METADATA
leetcron-0.1.0.dist-info/WHEEL
leetcron-0.1.0.dist-info/top_level.txt
leetcron-0.1.0.dist-info/RECORD
