Metadata-Version: 2.1
Name: leetcron
Version: 0.1.0
Summary: Sets up cron job that pushes Leetcode submissions to a Github repository
Home-page: https://github.com/JING1201/leetcron
Author: jlionwg
License: MIT
Platform: UNKNOWN
Requires-Python: >=3.5
License-File: LICENSE
Requires-Dist: python-crontab
Requires-Dist: browsercookie
Requires-Dist: PyGithub
